{
  "$schema": "https://ui.shadcn.com/schema/registry-item.json",
  "name": "liquid-metal-card-login",
  "registryDependencies": [
    "liquid-metal-card",
    "button",
    "input"
  ],
  "files": [
    {
      "path": "registry/default/examples/liquid-metal-card-login.tsx",
      "content": "import { Button } from '@/registry/default/ui/button';\nimport { Input } from '@/registry/default/ui/input';\nimport {\n  CardContent,\n  CardDescription,\n  CardHeader,\n  CardTitle,\n  LiquidMetalCard,\n} from '@/registry/default/ui/liquid-metal-card';\nimport { Github, User } from 'lucide-react';\n\nexport function LiquidMetalCardLogin() {\n  return (\n    <LiquidMetalCard\n      className='w-full max-w-sm'\n      speed={0.3}\n      repetition={3}\n      softness={0.8}\n      shiftRed={0.2}\n      shiftBlue={0.4}\n    >\n      <CardHeader className='text-center'>\n        <CardTitle>Welcome back</CardTitle>\n        <CardDescription>Sign in to your account</CardDescription>\n      </CardHeader>\n      <CardContent className='flex flex-col gap-4'>\n        <Input type='email' placeholder='Email address' className='h-10' />\n        <Input type='password' placeholder='Password' className='h-10' />\n        <Button className='w-full'>Sign In</Button>\n        <div className='relative'>\n          <div className='absolute inset-0 flex items-center'>\n            <div className='w-full border-t border-border' />\n          </div>\n          <div className='relative flex justify-center text-xs'>\n            <span className='bg-card px-2 text-muted-foreground'>\n              or continue with\n            </span>\n          </div>\n        </div>\n        <div className='grid grid-cols-2 gap-2'>\n          <Button variant='outline' className='gap-2'>\n            <Github className='size-4' />\n            GitHub\n          </Button>\n          <Button variant='outline' className='gap-2'>\n            <User className='size-4' />\n            Google\n          </Button>\n        </div>\n      </CardContent>\n    </LiquidMetalCard>\n  );\n}\n",
      "type": "registry:example"
    }
  ],
  "type": "registry:example"
}